nexushousekeeper/__init__.py
nexushousekeeper/mvnrepositoryhandler.py
nexushousekeeper/nexushousekeeper.py
nexushousekeeper-0.0.7.dist-info/entry_points.txt
nexushousekeeper-0.0.7.dist-info/LICENSE
nexushousekeeper-0.0.7.dist-info/WHEEL
nexushousekeeper-0.0.7.dist-info/METADATA
nexushousekeeper-0.0.7.dist-info/RECORD
