Metadata-Version: 2.1
Name: nexushousekeeper
Version: 0.0.7
Summary: A module to keep a nexus directory clean
Home-page: https://github.com/benDeMtp/NexusHouseKeeper
License: MIT
Keywords: nexus,nexus3
Author: Benjamin Raimondi
Author-email: benjamin.raimondi@gmail.com
Requires-Python: >=3.6,<4.0
Classifier: Environment :: Console
Classifier: License :: OSI Approved :: MIT License
Classifier: Operating System :: OS Independent
Classifier: Programming Language :: Python :: 3
Classifier: Programming Language :: Python :: 3.6
Classifier: Programming Language :: Python :: 3.7
Classifier: Programming Language :: Python :: 3.8
Classifier: Programming Language :: Python :: 3.9
Requires-Dist: hurry.filesize (==0.9)
Requires-Dist: requests (==2.25.0)
Requires-Dist: requests_futures (==1.0.0)
Requires-Dist: rich (>=9.4.0,<10.0.0)
Project-URL: Repository, https://github.com/benDeMtp/NexusHouseKeeper
